mailproc/__init__.py
mailproc/exceptions.py
mailproc/mailproc.py
mailproc/mailproc_email.py
mailproc/transports/__init__.py
mailproc/transports/base_receiver_transport.py
mailproc/transports/base_sender_transport.py
mailproc/transports/file_receiver_transport.py
mailproc/transports/file_sender_transport.py
mailproc/transports/imap_idle_receiver_transport.py
mailproc/transports/imap_receiver_transport.py
mailproc/transports/smtp_sender_transport.py
mailProc-0.6.0.dist-info/LICENSE
mailProc-0.6.0.dist-info/METADATA
mailProc-0.6.0.dist-info/WHEEL
mailProc-0.6.0.dist-info/top_level.txt
mailProc-0.6.0.dist-info/RECORD
